_pybddisasm.cp39-win_amd64.pyd
pybddisasm/__init__.py
pybddisasm/pybddisasm.c
pybddisasm/pybddisasm.i
pybddisasm/pybddisasm.py
pybddisasm-0.3.0.dist-info/LICENSE
pybddisasm-0.3.0.dist-info/METADATA
pybddisasm-0.3.0.dist-info/WHEEL
pybddisasm-0.3.0.dist-info/top_level.txt
pybddisasm-0.3.0.dist-info/RECORD
