Metadata-Version: 2.1
Name: pybddisasm
Version: 0.3.0
Summary: The Bitdefender disassembler Python wrapper
Home-page: https://github.com/bitdefender/bddisasm
Author: Bitdefender
License: Apache Software License
Platform: Windows
Platform: Linux
Classifier: Programming Language :: Python :: 3.7
Classifier: Programming Language :: Python :: 3.8
Classifier: Programming Language :: Python :: 3.9
Classifier: Programming Language :: Python :: 3.10
Classifier: Programming Language :: Python :: 3.11
Classifier: License :: OSI Approved :: Apache Software License
Classifier: Operating System :: Microsoft :: Windows
Classifier: Operating System :: POSIX :: Linux
Requires-Python: >=3.5
License-File: LICENSE
Requires-Dist: setuptools
